Metadata-Version: 2.1
Name: PyCoptimizer
Version: 0.1.2
Summary: Python Code Optimization using compilation flags
Home-page: UNKNOWN
Author: Leticia Figueiredo
Author-email: letfreirefigueiredo@gmail.com
License: Apache License
Platform: UNKNOWN
